resguard.py
resguard-0.1.dist-info/METADATA
resguard-0.1.dist-info/WHEEL
resguard-0.1.dist-info/top_level.txt
resguard-0.1.dist-info/RECORD
