Metadata-Version: 2.1
Name: resguard
Version: 0.1
Summary: UNKNOWN
Home-page: UNKNOWN
Author: Daniel Hilst Selli
Author-email: danielhilst@gmail.com
License: Apache-2.0
Platform: UNKNOWN
Requires-Python: >=3.6
